aquacroppy/__init__.py
aquacroppy/aos.py
aquacroppy/elements.py
aquacroppy/utils.py
aquacroppy-0.0.0.3.dist-info/LICENSE
aquacroppy-0.0.0.3.dist-info/METADATA
aquacroppy-0.0.0.3.dist-info/WHEEL
aquacroppy-0.0.0.3.dist-info/top_level.txt
aquacroppy-0.0.0.3.dist-info/RECORD
