Metadata-Version: 2.1
Name: aquacroppy
Version: 0.0.0.3
Summary: AquaCrop Python
Home-page: https://github.com/noah-de/aquacroppy
Author: Noah Spahn
Author-email: noah.de@gmail.com
License: UNKNOWN
Platform: UNKNOWN
Classifier: Programming Language :: Python :: 3
Classifier: Intended Audience :: Science/Research
Classifier: License :: OSI Approved :: GNU General Public License v3 (GPLv3)
Classifier: Operating System :: OS Independent
